TuXingKeJi/TuXingSDK.py
TuXingKeJi/__init__.py
TuXingKeJi/enumHelper.py
TuXingKeJi/peripheral.py
TuXingKeJi/serialHelper.py
tuxingkeji-0.0.10.dist-info/LICENSE
tuxingkeji-0.0.10.dist-info/METADATA
tuxingkeji-0.0.10.dist-info/WHEEL
tuxingkeji-0.0.10.dist-info/top_level.txt
tuxingkeji-0.0.10.dist-info/RECORD
