Metadata-Version: 2.1
Name: TuXingKeJi
Version: 0.0.10
Summary: A python package for TuXingKeJi UAV control
Author-email: chenghao <chenghao.wang@uphf.fr>
Project-URL: Homepage, https://github.com/martinWANG2014/TuXingKeJi_SDK
Project-URL: Bug Tracker, https://github.com/martinWANG2014/TuXingKeJi_SDK/issues
Classifier: Programming Language :: Python :: 3
Classifier: Programming Language :: Python :: 3.7
Classifier: Programming Language :: Python :: 3.8
Classifier: Programming Language :: Python :: 3.9
Classifier: Programming Language :: Python :: 3.10
Classifier: Programming Language :: Python :: 3.11
Classifier: License :: OSI Approved :: MIT License
Classifier: Operating System :: OS Independent
Requires-Python: >=3.7
License-File: LICENSE
Requires-Dist: strenum
Requires-Dist: pyserial
